{
  "location": "Kledering",
  "last_updated": "2026-01-10T16:23:08.974899+01:00",
  "source": "Geosphere",
  "forecast_type": "nowcast",
  "forecast_period": "3 hour",
  "resolution": "15 minute",
  "forecast_data": [
    {
      "time": "2026-01-10T15:15+00:00",
      "temperature": -3.09,
      "precipitation": 0.0,
      "dew_point": -5.02,
      "wind_direction": 356.9,
      "wind_speed": 4.88,
      "wind_gust": 7.56
    },
    {
      "time": "2026-01-10T15:30+00:00",
      "temperature": -3.48,
      "precipitation": 0.0,
      "dew_point": -5.53,
      "wind_direction": 358.7,
      "wind_speed": 4.88,
      "wind_gust": 7.56
    },
    {
      "time": "2026-01-10T15:45+00:00",
      "temperature": -3.88,
      "precipitation": 0.0,
      "dew_point": -6.05,
      "wind_direction": 359.6,
      "wind_speed": 4.93,
      "wind_gust": 7.62
    },
    {
      "time": "2026-01-10T16:00+00:00",
      "temperature": -4.17,
      "precipitation": 0.0,
      "dew_point": -6.47,
      "wind_direction": 359.6,
      "wind_speed": 5.05,
      "wind_gust": 7.82
    },
    {
      "time": "2026-01-10T16:15+00:00",
      "temperature": -4.25,
      "precipitation": 0.0,
      "dew_point": -6.65,
      "wind_direction": 359.4,
      "wind_speed": 5.03,
      "wind_gust": 7.79
    },
    {
      "time": "2026-01-10T16:30+00:00",
      "temperature": -4.32,
      "precipitation": 0.01,
      "dew_point": -6.84,
      "wind_direction": 359.2,
      "wind_speed": 5.01,
      "wind_gust": 7.76
    },
    {
      "time": "2026-01-10T16:45+00:00",
      "temperature": -4.44,
      "precipitation": 0.01,
      "dew_point": -7.08,
      "wind_direction": 359.0,
      "wind_speed": 4.99,
      "wind_gust": 7.73
    },
    {
      "time": "2026-01-10T17:00+00:00",
      "temperature": -4.6,
      "precipitation": 0.01,
      "dew_point": -7.39,
      "wind_direction": 358.8,
      "wind_speed": 4.98,
      "wind_gust": 7.7
    },
    {
      "time": "2026-01-10T17:15+00:00",
      "temperature": -4.75,
      "precipitation": 0.01,
      "dew_point": -7.57,
      "wind_direction": 358.0,
      "wind_speed": 4.94,
      "wind_gust": 7.72
    },
    {
      "time": "2026-01-10T17:30+00:00",
      "temperature": -4.92,
      "precipitation": 0.01,
      "dew_point": -7.77,
      "wind_direction": 357.0,
      "wind_speed": 4.91,
      "wind_gust": 7.75
    },
    {
      "time": "2026-01-10T17:45+00:00",
      "temperature": -5.1,
      "precipitation": 0.01,
      "dew_point": -7.99,
      "wind_direction": 355.8,
      "wind_speed": 4.88,
      "wind_gust": 7.81
    },
    {
      "time": "2026-01-10T18:00+00:00",
      "temperature": -5.29,
      "precipitation": 0.01,
      "dew_point": -8.22,
      "wind_direction": 354.5,
      "wind_speed": 4.84,
      "wind_gust": 7.88
    }
  ],
  "units": {
    "temperature": "degree_Celsius",
    "precipitation": "kg m-2",
    "dew_point": "degree_Celsius",
    "wind_direction": "m s-1",
    "wind_speed": "m s-1",
    "wind_gust": "m s-1"
  }
}