{
  "location": "Kledering",
  "last_updated": "2025-08-21T00:19:46.485301+02:00",
  "source": "Geosphere",
  "forecast_type": "nowcast",
  "forecast_period": "3 hour",
  "resolution": "15 minute",
  "forecast_data": [
    {
      "time": "2025-08-20T22:15+00:00",
      "temperature": 21.67,
      "precipitation": 0.0,
      "dew_point": 12.42,
      "wind_direction": 229.2,
      "wind_speed": 1.63,
      "wind_gust": 2.56
    },
    {
      "time": "2025-08-20T22:30+00:00",
      "temperature": 21.61,
      "precipitation": 0.0,
      "dew_point": 12.41,
      "wind_direction": 227.0,
      "wind_speed": 1.62,
      "wind_gust": 2.56
    },
    {
      "time": "2025-08-20T22:45+00:00",
      "temperature": 21.54,
      "precipitation": 0.0,
      "dew_point": 12.4,
      "wind_direction": 225.4,
      "wind_speed": 1.61,
      "wind_gust": 2.56
    },
    {
      "time": "2025-08-20T23:00+00:00",
      "temperature": 21.47,
      "precipitation": 0.0,
      "dew_point": 12.86,
      "wind_direction": 224.2,
      "wind_speed": 1.6,
      "wind_gust": 2.56
    },
    {
      "time": "2025-08-20T23:15+00:00",
      "temperature": 21.42,
      "precipitation": 0.0,
      "dew_point": 13.54,
      "wind_direction": 227.7,
      "wind_speed": 1.55,
      "wind_gust": 2.56
    },
    {
      "time": "2025-08-20T23:30+00:00",
      "temperature": 21.36,
      "precipitation": 0.0,
      "dew_point": 14.18,
      "wind_direction": 232.6,
      "wind_speed": 1.46,
      "wind_gust": 2.53
    },
    {
      "time": "2025-08-20T23:45+00:00",
      "temperature": 21.31,
      "precipitation": 0.0,
      "dew_point": 14.64,
      "wind_direction": 238.7,
      "wind_speed": 1.38,
      "wind_gust": 2.46
    },
    {
      "time": "2025-08-21T00:00+00:00",
      "temperature": 21.26,
      "precipitation": 0.0,
      "dew_point": 14.9,
      "wind_direction": 245.6,
      "wind_speed": 1.32,
      "wind_gust": 2.37
    },
    {
      "time": "2025-08-21T00:15+00:00",
      "temperature": 21.18,
      "precipitation": 0.0,
      "dew_point": 15.1,
      "wind_direction": 250.1,
      "wind_speed": 1.07,
      "wind_gust": 1.94
    },
    {
      "time": "2025-08-21T00:30+00:00",
      "temperature": 21.1,
      "precipitation": 0.0,
      "dew_point": 15.21,
      "wind_direction": 255.3,
      "wind_speed": 0.8,
      "wind_gust": 1.47
    },
    {
      "time": "2025-08-21T00:45+00:00",
      "temperature": 21.02,
      "precipitation": 0.0,
      "dew_point": 15.28,
      "wind_direction": 263.7,
      "wind_speed": 0.54,
      "wind_gust": 0.99
    },
    {
      "time": "2025-08-21T01:00+00:00",
      "temperature": 20.94,
      "precipitation": 0.0,
      "dew_point": 15.35,
      "wind_direction": 284.8,
      "wind_speed": 0.29,
      "wind_gust": 0.54
    }
  ],
  "units": {
    "temperature": "degree_Celsius",
    "precipitation": "kg m-2",
    "dew_point": "degree_Celsius",
    "wind_direction": "m s-1",
    "wind_speed": "m s-1",
    "wind_gust": "m s-1"
  }
}