{
  "location": "Kledering",
  "last_updated": "2025-10-10T08:32:50.119001+02:00",
  "source": "Geosphere",
  "forecast_type": "nowcast",
  "forecast_period": "3 hour",
  "resolution": "15 minute",
  "forecast_data": [
    {
      "time": "2025-10-10T06:30+00:00",
      "temperature": 12.34,
      "precipitation": 0.0,
      "dew_point": 9.46,
      "wind_direction": 294.0,
      "wind_speed": 3.19,
      "wind_gust": 5.29
    },
    {
      "time": "2025-10-10T06:45+00:00",
      "temperature": 12.58,
      "precipitation": 0.0,
      "dew_point": 9.45,
      "wind_direction": 294.8,
      "wind_speed": 3.19,
      "wind_gust": 5.29
    },
    {
      "time": "2025-10-10T07:00+00:00",
      "temperature": 12.91,
      "precipitation": 0.0,
      "dew_point": 9.39,
      "wind_direction": 295.6,
      "wind_speed": 3.18,
      "wind_gust": 5.29
    },
    {
      "time": "2025-10-10T07:15+00:00",
      "temperature": 13.2,
      "precipitation": 0.0,
      "dew_point": 9.5,
      "wind_direction": 294.4,
      "wind_speed": 3.21,
      "wind_gust": 5.31
    },
    {
      "time": "2025-10-10T07:30+00:00",
      "temperature": 13.49,
      "precipitation": 0.0,
      "dew_point": 9.6,
      "wind_direction": 293.2,
      "wind_speed": 3.23,
      "wind_gust": 5.35
    },
    {
      "time": "2025-10-10T07:45+00:00",
      "temperature": 13.74,
      "precipitation": 0.0,
      "dew_point": 9.73,
      "wind_direction": 292.0,
      "wind_speed": 3.26,
      "wind_gust": 5.4
    },
    {
      "time": "2025-10-10T08:00+00:00",
      "temperature": 13.96,
      "precipitation": 0.0,
      "dew_point": 9.88,
      "wind_direction": 290.8,
      "wind_speed": 3.28,
      "wind_gust": 5.45
    },
    {
      "time": "2025-10-10T08:15+00:00",
      "temperature": 14.16,
      "precipitation": 0.0,
      "dew_point": 9.84,
      "wind_direction": 292.2,
      "wind_speed": 3.53,
      "wind_gust": 5.93
    },
    {
      "time": "2025-10-10T08:30+00:00",
      "temperature": 14.35,
      "precipitation": 0.0,
      "dew_point": 9.8,
      "wind_direction": 293.3,
      "wind_speed": 3.78,
      "wind_gust": 6.42
    },
    {
      "time": "2025-10-10T08:45+00:00",
      "temperature": 14.53,
      "precipitation": 0.0,
      "dew_point": 9.77,
      "wind_direction": 294.4,
      "wind_speed": 4.03,
      "wind_gust": 6.91
    },
    {
      "time": "2025-10-10T09:00+00:00",
      "temperature": 14.71,
      "precipitation": 0.0,
      "dew_point": 9.75,
      "wind_direction": 295.3,
      "wind_speed": 4.28,
      "wind_gust": 7.4
    }
  ],
  "units": {
    "temperature": "degree_Celsius",
    "precipitation": "kg m-2",
    "dew_point": "degree_Celsius",
    "wind_direction": "m s-1",
    "wind_speed": "m s-1",
    "wind_gust": "m s-1"
  }
}