{
  "location": "Kledering",
  "last_updated": "2025-10-01T12:23:09.656499+02:00",
  "source": "Geosphere",
  "forecast_type": "nowcast",
  "forecast_period": "3 hour",
  "resolution": "15 minute",
  "forecast_data": [
    {
      "time": "2025-10-01T10:15+00:00",
      "temperature": 11.26,
      "precipitation": 0.0,
      "dew_point": 5.43,
      "wind_direction": 335.8,
      "wind_speed": 5.6,
      "wind_gust": 8.89
    },
    {
      "time": "2025-10-01T10:30+00:00",
      "temperature": 11.47,
      "precipitation": 0.0,
      "dew_point": 5.4,
      "wind_direction": 336.2,
      "wind_speed": 5.59,
      "wind_gust": 8.89
    },
    {
      "time": "2025-10-01T10:45+00:00",
      "temperature": 11.69,
      "precipitation": 0.0,
      "dew_point": 5.37,
      "wind_direction": 336.6,
      "wind_speed": 5.59,
      "wind_gust": 8.89
    },
    {
      "time": "2025-10-01T11:00+00:00",
      "temperature": 11.76,
      "precipitation": 0.0,
      "dew_point": 5.21,
      "wind_direction": 337.0,
      "wind_speed": 5.59,
      "wind_gust": 8.89
    },
    {
      "time": "2025-10-01T11:15+00:00",
      "temperature": 11.61,
      "precipitation": 0.0,
      "dew_point": 5.08,
      "wind_direction": 338.0,
      "wind_speed": 5.58,
      "wind_gust": 8.89
    },
    {
      "time": "2025-10-01T11:30+00:00",
      "temperature": 11.45,
      "precipitation": 0.0,
      "dew_point": 4.96,
      "wind_direction": 338.9,
      "wind_speed": 5.58,
      "wind_gust": 8.89
    },
    {
      "time": "2025-10-01T11:45+00:00",
      "temperature": 11.35,
      "precipitation": 0.0,
      "dew_point": 4.88,
      "wind_direction": 339.8,
      "wind_speed": 5.58,
      "wind_gust": 8.89
    },
    {
      "time": "2025-10-01T12:00+00:00",
      "temperature": 11.32,
      "precipitation": 0.01,
      "dew_point": 4.87,
      "wind_direction": 340.5,
      "wind_speed": 5.58,
      "wind_gust": 8.89
    },
    {
      "time": "2025-10-01T12:15+00:00",
      "temperature": 11.39,
      "precipitation": 0.01,
      "dew_point": 4.83,
      "wind_direction": 341.0,
      "wind_speed": 5.55,
      "wind_gust": 8.97
    },
    {
      "time": "2025-10-01T12:30+00:00",
      "temperature": 11.49,
      "precipitation": 0.01,
      "dew_point": 4.82,
      "wind_direction": 341.4,
      "wind_speed": 5.52,
      "wind_gust": 9.04
    },
    {
      "time": "2025-10-01T12:45+00:00",
      "temperature": 11.6,
      "precipitation": 0.01,
      "dew_point": 4.83,
      "wind_direction": 341.9,
      "wind_speed": 5.51,
      "wind_gust": 9.11
    },
    {
      "time": "2025-10-01T13:00+00:00",
      "temperature": 11.71,
      "precipitation": 0.01,
      "dew_point": 4.83,
      "wind_direction": 342.4,
      "wind_speed": 5.49,
      "wind_gust": 9.18
    }
  ],
  "units": {
    "temperature": "degree_Celsius",
    "precipitation": "kg m-2",
    "dew_point": "degree_Celsius",
    "wind_direction": "m s-1",
    "wind_speed": "m s-1",
    "wind_gust": "m s-1"
  }
}