{
  "location": "Kledering",
  "last_updated": "2025-10-03T05:30:04.162744+02:00",
  "source": "Geosphere",
  "forecast_type": "nowcast",
  "forecast_period": "3 hour",
  "resolution": "15 minute",
  "forecast_data": [
    {
      "time": "2025-10-03T03:30+00:00",
      "temperature": 3.12,
      "precipitation": 0.0,
      "dew_point": 0.24,
      "wind_direction": 312.6,
      "wind_speed": 3.25,
      "wind_gust": 5.46
    },
    {
      "time": "2025-10-03T03:45+00:00",
      "temperature": 2.94,
      "precipitation": 0.0,
      "dew_point": 0.22,
      "wind_direction": 310.4,
      "wind_speed": 3.25,
      "wind_gust": 5.46
    },
    {
      "time": "2025-10-03T04:00+00:00",
      "temperature": 2.84,
      "precipitation": 0.0,
      "dew_point": 0.08,
      "wind_direction": 307.7,
      "wind_speed": 3.27,
      "wind_gust": 5.46
    },
    {
      "time": "2025-10-03T04:15+00:00",
      "temperature": 2.76,
      "precipitation": 0.0,
      "dew_point": -0.11,
      "wind_direction": 308.9,
      "wind_speed": 3.29,
      "wind_gust": 5.46
    },
    {
      "time": "2025-10-03T04:30+00:00",
      "temperature": 2.68,
      "precipitation": 0.0,
      "dew_point": -0.31,
      "wind_direction": 308.7,
      "wind_speed": 3.32,
      "wind_gust": 5.46
    },
    {
      "time": "2025-10-03T04:45+00:00",
      "temperature": 2.56,
      "precipitation": 0.0,
      "dew_point": -0.46,
      "wind_direction": 302.1,
      "wind_speed": 3.44,
      "wind_gust": 5.64
    },
    {
      "time": "2025-10-03T05:00+00:00",
      "temperature": 2.41,
      "precipitation": 0.0,
      "dew_point": -0.55,
      "wind_direction": 292.3,
      "wind_speed": 3.72,
      "wind_gust": 6.16
    },
    {
      "time": "2025-10-03T05:15+00:00",
      "temperature": 2.8,
      "precipitation": 0.0,
      "dew_point": -0.56,
      "wind_direction": 294.5,
      "wind_speed": 3.69,
      "wind_gust": 6.14
    },
    {
      "time": "2025-10-03T05:30+00:00",
      "temperature": 3.17,
      "precipitation": 0.0,
      "dew_point": -0.55,
      "wind_direction": 296.7,
      "wind_speed": 3.66,
      "wind_gust": 6.14
    },
    {
      "time": "2025-10-03T05:45+00:00",
      "temperature": 3.54,
      "precipitation": 0.0,
      "dew_point": -0.52,
      "wind_direction": 299.0,
      "wind_speed": 3.64,
      "wind_gust": 6.14
    },
    {
      "time": "2025-10-03T06:00+00:00",
      "temperature": 3.9,
      "precipitation": 0.0,
      "dew_point": -0.49,
      "wind_direction": 301.3,
      "wind_speed": 3.63,
      "wind_gust": 6.15
    }
  ],
  "units": {
    "temperature": "degree_Celsius",
    "precipitation": "kg m-2",
    "dew_point": "degree_Celsius",
    "wind_direction": "m s-1",
    "wind_speed": "m s-1",
    "wind_gust": "m s-1"
  }
}